fw_http_metrics/__init__.py
fw_http_metrics/py.typed
fw_http_metrics-0.2.0.dist-info/LICENSE
fw_http_metrics-0.2.0.dist-info/WHEEL
fw_http_metrics-0.2.0.dist-info/METADATA
fw_http_metrics-0.2.0.dist-info/RECORD
