Metadata-Version: 2.1
Name: fw-http-metrics
Version: 0.2.0
Summary: FastAPI middleware for collecting and exposing Prometheus metrics.
Home-page: https://gitlab.com/flywheel-io/tools/lib/fw-http-metrics
License: MIT
Keywords: Flywheel,FastAPI,Prometheus,metrics
Author: Flywheel
Author-email: support@flywheel.io
Requires-Python: >=3.7,<4.0
Classifier: License :: OSI Approved :: MIT License
Classifier: Programming Language :: Python :: 3
Classifier: Programming Language :: Python :: 3.10
Classifier: Programming Language :: Python :: 3.7
Classifier: Programming Language :: Python :: 3.8
Classifier: Programming Language :: Python :: 3.9
Classifier: Topic :: Software Development :: Libraries :: Python Modules
Requires-Dist: fastapi (>=0,<1)
Requires-Dist: importlib-metadata (>=4.8.2,<5.0.0); python_version < "3.8"
Requires-Dist: prometheus-client (>=0,<1)
Project-URL: Documentation, https://gitlab.com/flywheel-io/tools/lib/fw-http-metrics
Project-URL: Repository, https://gitlab.com/flywheel-io/tools/lib/fw-http-metrics
